{"page_width": 2384.0, "page_height": 1684.0, "drawing_type": "Electrical lighting plan - Plan 100, Hus A Del 1, showing lighting fixtures, switches, outlets, sensors and DALI control wiring for KV. Läroboken 13", "scale": "1:50", "components": [{"id": "AI_P11_0", "type": "P11", "name": "Armatur (takarmatur, typ enligt armaturbilaga)", "en_name": "", "color": "#7a4a00", "size": null, "ok_height": null, "uk_height": null, "is_vertical": false, "fire_rating": null, "label": "P11 — 27 pcs", "bbox": null, "occurrences": 1, "measurement_type": "count", "quantity": 27.0, "unit": "pcs"}, {"id": "AI_P12_1", "type": "P12", "name": "Armatur (väggarmatur eller annan typ, enligt armaturbilaga)", "en_name": "", "color": "#2c5a3a", "size": null, "ok_height": null, "uk_height": null, "is_vertical": false, "fire_rating": null, "label": "P12 — 6 pcs", "bbox": null, "occurrences": 1, "measurement_type": "count", "quantity": 6.0, "unit": "pcs"}, {"id": "AI_P10_2", "type": "P10", "name": "Armatur (typ P10, enligt armaturbilaga)", "en_name": "", "color": "#1a5c6e", "size": null, "ok_height": null, "uk_height": null, "is_vertical": false, "fire_rating": null, "label": "P10 — 0 pcs", "bbox": null, "occurrences": 1, "measurement_type": "count", "quantity": 0.0, "unit": "pcs"}, {"id": "AI_D1_3", "type": "D1", "name": "Återfjädrande strömst. 1-pol med DALI, interfacemodul NKO 316-0200, 1ST modul per 4ST tändningar 1000 DFG", "en_name": "", "color": "#1a4a5c", "size": null, "ok_height": null, "uk_height": null, "is_vertical": false, "fire_rating": null, "label": "D1 — 3 pcs", "bbox": null, "occurrences": 1, "measurement_type": "count", "quantity": 3.0, "unit": "pcs"}, {"id": "AI_D2_4", "type": "D2", "name": "Återfjädrande strömst. 1-pol med DALI, interfacemodul NKO 316-0200, 1ST modul per 4ST tändningar 1000 DFG (variant D2)", "en_name": "", "color": "#6e3a1a", "size": null, "ok_height": null, "uk_height": null, "is_vertical": false, "fire_rating": null, "label": "D2 — 3 pcs", "bbox": null, "occurrences": 1, "measurement_type": "count", "quantity": 3.0, "unit": "pcs"}, {"id": "AI_T4_5", "type": "T4", "name": "Timer med valbar tillslagstid 35-120min och synlig indikeringslampa 1000 DFG", "en_name": "", "color": "#9c2c2c", "size": null, "ok_height": null, "uk_height": null, "is_vertical": false, "fire_rating": null, "label": "T4 — 4 pcs", "bbox": null, "occurrences": 1, "measurement_type": "count", "quantity": 4.0, "unit": "pcs"}, {"id": "AI_N7_6", "type": "N7", "name": "Närvarodetektor NKO 941-1530050 Master, stampläggning (takphos)", "en_name": "", "color": "#1a4a5c", "size": null, "ok_height": null, "uk_height": null, "is_vertical": false, "fire_rating": null, "label": "N7 — 0 pcs", "bbox": null, "occurrences": 1, "measurement_type": "count", "quantity": 0.0, "unit": "pcs"}, {"id": "AI_N6_7", "type": "N6", "name": "Närvarodetektor NKO 941-1530030 Slav, stampläggning (takphos)", "en_name": "", "color": "#4a2c7a", "size": null, "ok_height": null, "uk_height": null, "is_vertical": false, "fire_rating": null, "label": "N6 — 1 pcs", "bbox": null, "occurrences": 1, "measurement_type": "count", "quantity": 1.0, "unit": "pcs"}, {"id": "AI_V11_8", "type": "V11", "name": "2-vägguttag utan U-tak för belysning", "en_name": "", "color": "#9c2c2c", "size": null, "ok_height": null, "uk_height": null, "is_vertical": false, "fire_rating": null, "label": "V11 — 0 pcs", "bbox": null, "occurrences": 1, "measurement_type": "count", "quantity": 0.0, "unit": "pcs"}, {"id": "AI_V17_9", "type": "V17", "name": "2-vägguttag utan U-tak för belysning (typ V17)", "en_name": "", "color": "#6e3a1a", "size": null, "ok_height": null, "uk_height": null, "is_vertical": false, "fire_rating": null, "label": "V17 — 2 pcs", "bbox": null, "occurrences": 1, "measurement_type": "count", "quantity": 2.0, "unit": "pcs"}, {"id": "AI_CE_10", "type": "CE", "name": "2-vägguttag IP44 900 DFG", "en_name": "", "color": "#9c2c2c", "size": null, "ok_height": "900", "uk_height": null, "is_vertical": false, "fire_rating": null, "label": "CE — 0 pcs", "bbox": null, "occurrences": 1, "measurement_type": "count", "quantity": 0.0, "unit": "pcs"}, {"id": "AI_500.5_11", "type": "500.5", "name": "Snabbkopplingsfördelaren 5-pol, 5-vägs 770-767 (WAGO snabbkopplingssystem)", "en_name": "", "color": "#9c2c2c", "size": null, "ok_height": null, "uk_height": null, "is_vertical": false, "fire_rating": null, "label": "500.5 — 0 pcs", "bbox": null, "occurrences": 1, "measurement_type": "count", "quantity": 0.0, "unit": "pcs"}, {"id": "AI_W1_12", "type": "W1", "name": "Sladdställ 5015 1-pol WAGO snabbkopplingssystem", "en_name": "", "color": "#9c2c2c", "size": null, "ok_height": null, "uk_height": null, "is_vertical": false, "fire_rating": null, "label": "W1 — 34 pcs", "bbox": null, "occurrences": 1, "measurement_type": "count", "quantity": 34.0, "unit": "pcs"}, {"id": "AI_W2_13", "type": "W2", "name": "Sladdställ 5015 3-pol WAGO snabbkopplingssystem", "en_name": "", "color": "#1a5c6e", "size": null, "ok_height": null, "uk_height": null, "is_vertical": false, "fire_rating": null, "label": "W2 — 1 pcs", "bbox": null, "occurrences": 1, "measurement_type": "count", "quantity": 1.0, "unit": "pcs"}, {"id": "AI_W3_14", "type": "W3", "name": "Sladdställ 5015 3-pol WAGO snabbkopplingssystem (variant W3)", "en_name": "", "color": "#7a4a00", "size": null, "ok_height": null, "uk_height": null, "is_vertical": false, "fire_rating": null, "label": "W3 — 0 pcs", "bbox": null, "occurrences": 1, "measurement_type": "count", "quantity": 0.0, "unit": "pcs"}, {"id": "AI_FH_15", "type": "FH", "name": "Pendelupphängning / fästanordning för armatur (FH-hängning)", "en_name": "", "color": "#6e3a1a", "size": null, "ok_height": null, "uk_height": null, "is_vertical": false, "fire_rating": null, "label": "FH — 6 pcs", "bbox": null, "occurrences": 1, "measurement_type": "count", "quantity": 6.0, "unit": "pcs"}, {"id": "AI_NKO_NARVARO_MASTER_16", "type": "NKO_NARVARO_MASTER", "name": "Närvarodetektor NKO 941-1530050 Master", "en_name": "", "color": "#2c5a3a", "size": null, "ok_height": null, "uk_height": null, "is_vertical": false, "fire_rating": null, "label": "NKO_NARVARO_MASTER — 2 pcs", "bbox": null, "occurrences": 1, "measurement_type": "count", "quantity": 2.0, "unit": "pcs"}, {"id": "AI_KS-B_17", "type": "KS-B", "name": "Kopplingsdosa för anslutning av armaturer i ventilationsaggregat / brandskåp", "en_name": "", "color": "#1a4a5c", "size": null, "ok_height": null, "uk_height": null, "is_vertical": false, "fire_rating": null, "label": "KS-B — 2 pcs", "bbox": null, "occurrences": 1, "measurement_type": "count", "quantity": 2.0, "unit": "pcs"}, {"id": "AI_I10_18", "type": "I10", "name": "I10", "en_name": "", "color": "#7a4a00", "size": null, "ok_height": null, "uk_height": null, "is_vertical": false, "fire_rating": null, "label": "I10 — 8 pcs", "bbox": null, "occurrences": 1, "measurement_type": "count", "quantity": 8.0, "unit": "pcs"}, {"id": "AI_V18_19", "type": "V18", "name": "V18", "en_name": "", "color": "#1a4a2c", "size": null, "ok_height": null, "uk_height": null, "is_vertical": false, "fire_rating": null, "label": "V18 — 1 pcs", "bbox": null, "occurrences": 1, "measurement_type": "count", "quantity": 1.0, "unit": "pcs"}, {"id": "AI_T2_20", "type": "T2", "name": "T2", "en_name": "", "color": "#6e3a1a", "size": null, "ok_height": null, "uk_height": null, "is_vertical": false, "fire_rating": null, "label": "T2 — 2 pcs", "bbox": null, "occurrences": 1, "measurement_type": "count", "quantity": 2.0, "unit": "pcs"}, {"id": "AI_F2_21", "type": "F2", "name": "F2", "en_name": "", "color": "#9c2c2c", "size": null, "ok_height": null, "uk_height": null, "is_vertical": false, "fire_rating": null, "label": "F2 — 10 pcs", "bbox": null, "occurrences": 1, "measurement_type": "count", "quantity": 10.0, "unit": "pcs"}, {"id": "AI_F1_22", "type": "F1", "name": "F1", "en_name": "", "color": "#1a4a2c", "size": null, "ok_height": null, "uk_height": null, "is_vertical": false, "fire_rating": null, "label": "F1 — 15 pcs", "bbox": null, "occurrences": 1, "measurement_type": "count", "quantity": 15.0, "unit": "pcs"}, {"id": "AI_N1-R_23", "type": "N1-R", "name": "N1-R", "en_name": "", "color": "#6e3a1a", "size": null, "ok_height": null, "uk_height": null, "is_vertical": false, "fire_rating": null, "label": "N1-R — 5 pcs", "bbox": null, "occurrences": 1, "measurement_type": "count", "quantity": 5.0, "unit": "pcs"}, {"id": "AI_N1_24", "type": "N1", "name": "N1", "en_name": "", "color": "#1a4a2c", "size": null, "ok_height": null, "uk_height": null, "is_vertical": false, "fire_rating": null, "label": "N1 — 2 pcs", "bbox": null, "occurrences": 1, "measurement_type": "count", "quantity": 2.0, "unit": "pcs"}, {"id": "AI_D4_25", "type": "D4", "name": "D4", "en_name": "", "color": "#9c2c2c", "size": null, "ok_height": null, "uk_height": null, "is_vertical": false, "fire_rating": null, "label": "D4 — 1 pcs", "bbox": null, "occurrences": 1, "measurement_type": "count", "quantity": 1.0, "unit": "pcs"}, {"id": "AI_F5_26", "type": "F5", "name": "F5", "en_name": "", "color": "#2c5a3a", "size": null, "ok_height": null, "uk_height": null, "is_vertical": false, "fire_rating": null, "label": "F5 — 3 pcs", "bbox": null, "occurrences": 1, "measurement_type": "count", "quantity": 3.0, "unit": "pcs"}, {"id": "AI_G1_27", "type": "G1", "name": "G1", "en_name": "", "color": "#9c2c2c", "size": null, "ok_height": null, "uk_height": null, "is_vertical": false, "fire_rating": null, "label": "G1 — 1 pcs", "bbox": null, "occurrences": 1, "measurement_type": "count", "quantity": 1.0, "unit": "pcs"}, {"id": "AI_D5_28", "type": "D5", "name": "D5", "en_name": "", "color": "#1a5c6e", "size": null, "ok_height": null, "uk_height": null, "is_vertical": false, "fire_rating": null, "label": "D5 — 1 pcs", "bbox": null, "occurrences": 1, "measurement_type": "count", "quantity": 1.0, "unit": "pcs"}, {"id": "AI_T1_29", "type": "T1", "name": "T1", "en_name": "", "color": "#1a4a5c", "size": null, "ok_height": null, "uk_height": null, "is_vertical": false, "fire_rating": null, "label": "T1 — 2 pcs", "bbox": null, "occurrences": 1, "measurement_type": "count", "quantity": 2.0, "unit": "pcs"}], "summary": [{"system": "P11", "name": "Armatur (takarmatur, typ enligt armaturbilaga)", "orientation": "horizontal", "width_mm": null, "ok_ofg_mm": null, "uk_ofg_mm": null, "fire_rating": null, "measurement_type": "count", "unit": "pcs", "count": 27, "count_grid_a": 27, "count_grid_b": 27, "count_grid_c": 27, "count_confidence": "high"}, {"system": "P12", "name": "Armatur (väggarmatur eller annan typ, enligt armaturbilaga)", "orientation": "horizontal", "width_mm": null, "ok_ofg_mm": null, "uk_ofg_mm": null, "fire_rating": null, "measurement_type": "count", "unit": "pcs", "count": 6, "count_grid_a": 6, "count_grid_b": 6, "count_grid_c": 6, "count_confidence": "high"}, {"system": "P10", "name": "Armatur (typ P10, enligt armaturbilaga)", "orientation": "horizontal", "width_mm": null, "ok_ofg_mm": null, "uk_ofg_mm": null, "fire_rating": null, "measurement_type": "count", "unit": "pcs", "count": 0, "count_grid_a": 0, "count_grid_b": 0, "count_grid_c": 0, "count_confidence": "high"}, {"system": "D1", "name": "Återfjädrande strömst. 1-pol med DALI, interfacemodul NKO 316-0200, 1ST modul per 4ST tändningar 1000 DFG", "orientation": "horizontal", "width_mm": null, "ok_ofg_mm": null, "uk_ofg_mm": null, "fire_rating": null, "measurement_type": "count", "unit": "pcs", "count": 3, "count_grid_a": 3, "count_grid_b": 3, "count_grid_c": 3, "count_confidence": "high"}, {"system": "D2", "name": "Återfjädrande strömst. 1-pol med DALI, interfacemodul NKO 316-0200, 1ST modul per 4ST tändningar 1000 DFG (variant D2)", "orientation": "horizontal", "width_mm": null, "ok_ofg_mm": null, "uk_ofg_mm": null, "fire_rating": null, "measurement_type": "count", "unit": "pcs", "count": 3, "count_grid_a": 3, "count_grid_b": 3, "count_grid_c": 3, "count_confidence": "high"}, {"system": "T4", "name": "Timer med valbar tillslagstid 35-120min och synlig indikeringslampa 1000 DFG", "orientation": "horizontal", "width_mm": null, "ok_ofg_mm": null, "uk_ofg_mm": null, "fire_rating": null, "measurement_type": "count", "unit": "pcs", "count": 4, "count_grid_a": 4, "count_grid_b": 4, "count_grid_c": 4, "count_confidence": "high"}, {"system": "N7", "name": "Närvarodetektor NKO 941-1530050 Master, stampläggning (takphos)", "orientation": "horizontal", "width_mm": null, "ok_ofg_mm": null, "uk_ofg_mm": null, "fire_rating": null, "measurement_type": "count", "unit": "pcs", "count": 0, "count_grid_a": 0, "count_grid_b": 0, "count_grid_c": 0, "count_confidence": "high"}, {"system": "N6", "name": "Närvarodetektor NKO 941-1530030 Slav, stampläggning (takphos)", "orientation": "horizontal", "width_mm": null, "ok_ofg_mm": null, "uk_ofg_mm": null, "fire_rating": null, "measurement_type": "count", "unit": "pcs", "count": 1, "count_grid_a": 1, "count_grid_b": 1, "count_grid_c": 1, "count_confidence": "high"}, {"system": "V11", "name": "2-vägguttag utan U-tak för belysning", "orientation": "horizontal", "width_mm": null, "ok_ofg_mm": null, "uk_ofg_mm": null, "fire_rating": null, "measurement_type": "count", "unit": "pcs", "count": 0, "count_grid_a": 0, "count_grid_b": 0, "count_grid_c": 0, "count_confidence": "high"}, {"system": "V17", "name": "2-vägguttag utan U-tak för belysning (typ V17)", "orientation": "horizontal", "width_mm": null, "ok_ofg_mm": null, "uk_ofg_mm": null, "fire_rating": null, "measurement_type": "count", "unit": "pcs", "count": 2, "count_grid_a": 2, "count_grid_b": 2, "count_grid_c": 2, "count_confidence": "high"}, {"system": "CE", "name": "2-vägguttag IP44 900 DFG", "orientation": "horizontal", "width_mm": null, "ok_ofg_mm": 900, "uk_ofg_mm": null, "fire_rating": null, "measurement_type": "count", "unit": "pcs", "count": 0, "count_grid_a": 0, "count_grid_b": 0, "count_grid_c": 0, "count_confidence": "high"}, {"system": "500.5", "name": "Snabbkopplingsfördelaren 5-pol, 5-vägs 770-767 (WAGO snabbkopplingssystem)", "orientation": "horizontal", "width_mm": null, "ok_ofg_mm": null, "uk_ofg_mm": null, "fire_rating": null, "measurement_type": "count", "unit": "pcs", "count": 0, "count_grid_a": 0, "count_grid_b": 0, "count_grid_c": 0, "count_confidence": "high"}, {"system": "W1", "name": "Sladdställ 5015 1-pol WAGO snabbkopplingssystem", "orientation": "horizontal", "width_mm": null, "ok_ofg_mm": null, "uk_ofg_mm": null, "fire_rating": null, "measurement_type": "count", "unit": "pcs", "count": 34, "count_grid_a": 34, "count_grid_b": 34, "count_grid_c": 34, "count_confidence": "high"}, {"system": "W2", "name": "Sladdställ 5015 3-pol WAGO snabbkopplingssystem", "orientation": "horizontal", "width_mm": null, "ok_ofg_mm": null, "uk_ofg_mm": null, "fire_rating": null, "measurement_type": "count", "unit": "pcs", "count": 1, "count_grid_a": 1, "count_grid_b": 1, "count_grid_c": 1, "count_confidence": "high"}, {"system": "W3", "name": "Sladdställ 5015 3-pol WAGO snabbkopplingssystem (variant W3)", "orientation": "horizontal", "width_mm": null, "ok_ofg_mm": null, "uk_ofg_mm": null, "fire_rating": null, "measurement_type": "count", "unit": "pcs", "count": 0, "count_grid_a": 0, "count_grid_b": 0, "count_grid_c": 0, "count_confidence": "high"}, {"system": "FH", "name": "Pendelupphängning / fästanordning för armatur (FH-hängning)", "orientation": "horizontal", "width_mm": null, "ok_ofg_mm": null, "uk_ofg_mm": null, "fire_rating": null, "measurement_type": "count", "unit": "pcs", "count": 6, "count_grid_a": 6, "count_grid_b": 0, "count_grid_c": 6, "count_confidence": "medium"}, {"system": "NKO_NARVARO_MASTER", "name": "Närvarodetektor NKO 941-1530050 Master", "orientation": "horizontal", "width_mm": null, "ok_ofg_mm": null, "uk_ofg_mm": null, "fire_rating": null, "measurement_type": "count", "unit": "pcs", "count": 2, "count_grid_a": 2, "count_grid_b": 2, "count_grid_c": 2, "count_confidence": "high"}, {"system": "KS-B", "name": "Kopplingsdosa för anslutning av armaturer i ventilationsaggregat / brandskåp", "orientation": "horizontal", "width_mm": null, "ok_ofg_mm": null, "uk_ofg_mm": null, "fire_rating": null, "measurement_type": "count", "unit": "pcs", "count": 2, "count_grid_a": 1, "count_grid_b": 2, "count_grid_c": 2, "count_confidence": "medium"}, {"system": "I10", "name": "I10", "orientation": "horizontal", "width_mm": null, "ok_ofg_mm": null, "uk_ofg_mm": null, "fire_rating": null, "measurement_type": "count", "unit": "pcs", "count": 8, "count_grid_a": 8, "count_grid_b": 8, "count_grid_c": 8, "count_confidence": "high"}, {"system": "V18", "name": "V18", "orientation": "horizontal", "width_mm": null, "ok_ofg_mm": null, "uk_ofg_mm": null, "fire_rating": null, "measurement_type": "count", "unit": "pcs", "count": 1, "count_grid_a": 1, "count_grid_b": 1, "count_grid_c": 1, "count_confidence": "high"}, {"system": "T2", "name": "T2", "orientation": "horizontal", "width_mm": null, "ok_ofg_mm": null, "uk_ofg_mm": null, "fire_rating": null, "measurement_type": "count", "unit": "pcs", "count": 2, "count_grid_a": 2, "count_grid_b": 2, "count_grid_c": 2, "count_confidence": "high"}, {"system": "F2", "name": "F2", "orientation": "horizontal", "width_mm": null, "ok_ofg_mm": null, "uk_ofg_mm": null, "fire_rating": null, "measurement_type": "count", "unit": "pcs", "count": 10, "count_grid_a": 10, "count_grid_b": 10, "count_grid_c": 10, "count_confidence": "high"}, {"system": "F1", "name": "F1", "orientation": "horizontal", "width_mm": null, "ok_ofg_mm": null, "uk_ofg_mm": null, "fire_rating": null, "measurement_type": "count", "unit": "pcs", "count": 15, "count_grid_a": 15, "count_grid_b": 15, "count_grid_c": 15, "count_confidence": "high"}, {"system": "N1-R", "name": "N1-R", "orientation": "horizontal", "width_mm": null, "ok_ofg_mm": null, "uk_ofg_mm": null, "fire_rating": null, "measurement_type": "count", "unit": "pcs", "count": 5, "count_grid_a": 5, "count_grid_b": 5, "count_grid_c": 5, "count_confidence": "high"}, {"system": "N1", "name": "N1", "orientation": "horizontal", "width_mm": null, "ok_ofg_mm": null, "uk_ofg_mm": null, "fire_rating": null, "measurement_type": "count", "unit": "pcs", "count": 2, "count_grid_a": 2, "count_grid_b": 2, "count_grid_c": 2, "count_confidence": "high"}, {"system": "D4", "name": "D4", "orientation": "horizontal", "width_mm": null, "ok_ofg_mm": null, "uk_ofg_mm": null, "fire_rating": null, "measurement_type": "count", "unit": "pcs", "count": 1, "count_grid_a": 1, "count_grid_b": 1, "count_grid_c": 1, "count_confidence": "high"}, {"system": "F5", "name": "F5", "orientation": "horizontal", "width_mm": null, "ok_ofg_mm": null, "uk_ofg_mm": null, "fire_rating": null, "measurement_type": "count", "unit": "pcs", "count": 3, "count_grid_a": 3, "count_grid_b": 3, "count_grid_c": 3, "count_confidence": "high"}, {"system": "G1", "name": "G1", "orientation": "horizontal", "width_mm": null, "ok_ofg_mm": null, "uk_ofg_mm": null, "fire_rating": null, "measurement_type": "count", "unit": "pcs", "count": 1, "count_grid_a": 1, "count_grid_b": 1, "count_grid_c": 1, "count_confidence": "high"}, {"system": "D5", "name": "D5", "orientation": "horizontal", "width_mm": null, "ok_ofg_mm": null, "uk_ofg_mm": null, "fire_rating": null, "measurement_type": "count", "unit": "pcs", "count": 1, "count_grid_a": 1, "count_grid_b": 1, "count_grid_c": 1, "count_confidence": "high"}, {"system": "T1", "name": "T1", "orientation": "horizontal", "width_mm": null, "ok_ofg_mm": null, "uk_ofg_mm": null, "fire_rating": null, "measurement_type": "count", "unit": "pcs", "count": 2, "count_grid_a": 2, "count_grid_b": 2, "count_grid_c": 2, "count_confidence": "high"}], "extraction_mode": "ai"}